odoo10_addon_stock_picking_package_preparation_line-10.0.1.0.4-py2.7-nspkg.pth
odoo/addons/stock_picking_package_preparation_line/README.rst
odoo/addons/stock_picking_package_preparation_line/__init__.py
odoo/addons/stock_picking_package_preparation_line/__manifest__.py
odoo/addons/stock_picking_package_preparation_line/i18n/ca.po
odoo/addons/stock_picking_package_preparation_line/i18n/de.po
odoo/addons/stock_picking_package_preparation_line/i18n/en.po
odoo/addons/stock_picking_package_preparation_line/i18n/es.po
odoo/addons/stock_picking_package_preparation_line/i18n/es_MX.po
odoo/addons/stock_picking_package_preparation_line/i18n/fi.po
odoo/addons/stock_picking_package_preparation_line/i18n/fr.po
odoo/addons/stock_picking_package_preparation_line/i18n/hr.po
odoo/addons/stock_picking_package_preparation_line/i18n/it.po
odoo/addons/stock_picking_package_preparation_line/i18n/nl_NL.po
odoo/addons/stock_picking_package_preparation_line/i18n/pt.po
odoo/addons/stock_picking_package_preparation_line/i18n/pt_BR.po
odoo/addons/stock_picking_package_preparation_line/i18n/sl.po
odoo/addons/stock_picking_package_preparation_line/i18n/stock_picking_package_preparation_line.pot
odoo/addons/stock_picking_package_preparation_line/i18n/tr.po
odoo/addons/stock_picking_package_preparation_line/i18n/tr_TR.po
odoo/addons/stock_picking_package_preparation_line/models/__init__.py
odoo/addons/stock_picking_package_preparation_line/models/ir_config.py
odoo/addons/stock_picking_package_preparation_line/models/res_company.py
odoo/addons/stock_picking_package_preparation_line/models/stock_move.py
odoo/addons/stock_picking_package_preparation_line/models/stock_picking_package_preparation.py
odoo/addons/stock_picking_package_preparation_line/models/stock_picking_package_preparation_line.py
odoo/addons/stock_picking_package_preparation_line/security/ir.model.access.csv
odoo/addons/stock_picking_package_preparation_line/security/package_preparation_line_security.xml
odoo10_addon_stock_picking_package_preparation_line-10.0.1.0.4.dist-info/METADATA
odoo10_addon_stock_picking_package_preparation_line-10.0.1.0.4.dist-info/RECORD
odoo10_addon_stock_picking_package_preparation_line-10.0.1.0.4.dist-info/WHEEL
odoo10_addon_stock_picking_package_preparation_line-10.0.1.0.4.dist-info/namespace_packages.txt
odoo10_addon_stock_picking_package_preparation_line-10.0.1.0.4.dist-info/top_level.txt
