Metadata-Version: 2.1
Name: odoo10-addon-stock-picking-package-preparation-line
Version: 10.0.1.0.4
Summary: Stock Picking Package Preparation Line
Home-page: http://www.apuliasoftware.it
Author: Apulia Software srl, Odoo Italia Network,Odoo Community Association (OCA)
Author-email: support@odoo-community.org
License: AGPL-3
Platform: UNKNOWN
Classifier: Programming Language :: Python
Classifier: Framework :: Odoo
Classifier: License :: OSI Approved :: GNU Affero General Public License v3
Requires-Python: ~=2.7
Requires-Dist: odoo10-addon-stock-picking-package-preparation
Requires-Dist: odoo (<10.1dev,>=10.0)
